<?xml version="1.0"?>
<!DOCTYPE dmodule [
<!ENTITY ICN-MTPA-A-G14100-A-MDMKD-00001-A-001-01 SYSTEM "ICN-MTPA-A-G14100-A-MDMKD-00001-A-001-01.cgm" NDATA cgm>
<!NOTATION cgm PUBLIC "-//USA-DOD//NOTATION Computer Graphics Metafile//EN">
]>
<dmodule xsi:noNamespaceSchemaLocation="http://www.s1000d.org/S1000D_4-1/xml_schema_flat/descript.xsd" xmlns:xsi="http://www.w3.org/2001/XMLSchema-instance" xmlns:rdf="http://www.w3.org/1999/02/22-rdf-syntax-ns#" xmlns:dc="http://www.purl.org/dc/elements/1.1/" xmlns:xlink="http://www.w3.org/1999/xlink">
<identAndStatusSection>
<dmAddress>
<dmIdent>
<dmCode modelIdentCode="MTPA" systemDiffCode="A" systemCode="G1" subSystemCode="4" subSubSystemCode="1" assyCode="00" disassyCode="00" disassyCodeVariant="A" infoCode="040" infoCodeVariant="A" itemLocationCode="A"></dmCode>
<language countryIsoCode="RU" languageIsoCode="ru"></language>
<issueInfo issueNumber="001" inWork="01"></issueInfo>
</dmIdent>
<dmAddressItems>
<issueDate year="2025" month="05" day="30"></issueDate>
<dmTitle>
<techName>Камера</techName>
<infoName>Описание</infoName>
</dmTitle>
</dmAddressItems>
</dmAddress>
<dmStatus issueType="new">
<security securityClassification="01"></security>
<responsiblePartnerCompany enterpriseCode="MDMKD">
<enterpriseName>МОДУЛЬ МКД</enterpriseName>
</responsiblePartnerCompany>
<originator enterpriseCode="MDMKD">
<enterpriseName>МОДУЛЬ МКД</enterpriseName>
</originator>
<applic>
<displayText>
<simplePara>ВСЕ</simplePara>
</displayText>
</applic>
<brexDmRef>
<dmRef xlink:type="simple" xlink:actuate="onRequest" xlink:show="replace" xlink:href="URN:S1000D:DMC-S1000D-E-04-10-0301-00A-022A-D">
<dmRefIdent>
<dmCode modelIdentCode="S1000D" systemDiffCode="E" systemCode="04" subSystemCode="1" subSubSystemCode="0" assyCode="0301" disassyCode="00" disassyCodeVariant="A" infoCode="022" infoCodeVariant="A" itemLocationCode="D"></dmCode>
</dmRefIdent>
</dmRef>
</brexDmRef>
<qualityAssurance>
<unverified></unverified>
</qualityAssurance>
</dmStatus>
</identAndStatusSection>
<content>
<description>
<levelledPara>
<title>Общие сведения</title>
<levelledPara>
<title>Назначение</title>
<para>
				Камера предназначена для точного выравнивания траверсы над модулем и контроля попадания такелажного элемента модуля в замок.</para>
</levelledPara>
<levelledPara>
<title>Состав</title>
<para>В состав траверсы входят четыре одинаковые камеры. В состав одной камеры входят:</para>
<para>
<randomList>
<listItem>
<para>видеокамера (1 шт.);</para>
</listItem>
<listItem>
<para>короб камеры (1 шт.);</para>
</listItem>
<listItem>
<para>крышка камеры (1 шт.).</para>
</listItem>
</randomList>
</para>
</levelledPara>
</levelledPara>
<levelledPara>
<title>Размещение компонентов</title>
<para>
			Камеры установлены на кронштейны видеокамер, размещенные на замках.</para>
</levelledPara>
<levelledPara>
<title>Описание</title>
<para>
<internalRef internalRefId="fig-001" internalRefTargetType="irtt01" xlink:href="#fig-001"></internalRef>
</para>
<para>Камера представляет собой сборную конструкцию, состоящую из видеокамеры, корба и крышки камеры.</para>
<para>Видеокамера выполнена в пыле-влагозащищенном корпусе со степенью защиты IP67. Короб и крышка камеры предназначены для установки видеокамеры на кронштейн. Короб камеры устанавливается непосредственно  на кронштейн, видеокамера – на крышку, которая фиксируется в коробе с помощью трех болтов.</para>
<figure id="fig-001">
<title>Камера</title>
<graphic infoEntityIdent="ICN-MTPA-A-G14100-A-MDMKD-00001-A-001-01" xlink:href="ICN-MTPA-A-G14100-A-MDMKD-00001-A-001-01.cgm" reproductionHeight="210mm" reproductionWidth="170mm" id="fig-001-gra-001">
<hotspot id="fig-001-gra-001-hot-001" applicationStructureIdent="AUTOID_001" applicationStructureName="ВИДЕОКАМЕРА"></hotspot>
<hotspot id="fig-001-gra-001-hot-002" applicationStructureIdent="AUTOID_010" applicationStructureName="КРЫШКА КАМЕРЫ"></hotspot>
<hotspot id="fig-001-gra-001-hot-003" applicationStructureIdent="AUTOID_017" applicationStructureName="КОРОБ КАМЕРЫ"></hotspot>
</graphic>
</figure>
</levelledPara>
</description>
</content>
</dmodule>
